rcaudio/__init__.py
rcaudio/base_analyzer.py
rcaudio/beat_analyzer.py
rcaudio/core_recorder.py
rcaudio/feature_analyzer.py
rcaudio/simple_recorder.py
rcaudio/volume_analyzer.py
rcaudio-0.0.3.dist-info/METADATA
rcaudio-0.0.3.dist-info/RECORD
rcaudio-0.0.3.dist-info/WHEEL
rcaudio-0.0.3.dist-info/top_level.txt
