Metadata-Version: 2.1
Name: rcaudio
Version: 0.0.3
Summary: A real-time audio recording & analyzing library
Home-page: https://github.com/mhy12345/rcaudio
Author: mhy12345
Author-email: maohanyang789@163.com
License: UNKNOWN
Platform: UNKNOWN
Classifier: Programming Language :: Python :: 3
Classifier: License :: OSI Approved :: MIT License
Classifier: Operating System :: OS Independent
